[
  {"traAccount" : {
    "accId": 2
  },
    "traDestinationAccount":  {"accId": 1},
    "traAmount": 1000,
    "traDescription": "A"
  },
  {"traAccount" : {
    "accId": 1
  },
    "traDestinationAccount": {"accId": 2},
    "traAmount": 62300,
    "traDescription": "A"
  },
  {"traAccount" : {
    "accId": 1
  },
    "traDestinationAccount":  {"accId": 2},
    "traAmount": 12310,
    "traDescription": "A"
  },
  {"traAccount" : {
    "accId": 1
  },
    "traDestinationAccount":  {"accId": 2},
    "traAmount": 123120,
    "traDescription": "A"
  },
  {"traAccount" : {
    "accId": 2
  },
    "traDestinationAccount":  {"accId": 1},
    "traAmount": 422300,
    "traDescription": "A"
  },
  {"traAccount" :{
    "accId": 1
  },
    "traDestinationAccount":  {"accId": 2},
    "traAmount": 3242300,
    "traDescription": "A"
  },
  {"traAccount" :{
    "accId": 2
  },
    "traDestinationAccount":  {"accId": 1},
    "traAmount": 324200,
    "traDescription": "A"
  },
  {"traAccount" : {
    "accId": 1
  },
    "traDestinationAccount":  {"accId": 2},
    "traAmount": 4000,
    "traDescription": "A"
  },
  {"traAccount" : {
    "accId": 2
  },
    "traDestinationAccount":  {"accId": 1},
    "traAmount": 5000,
    "traDescription": "A"
  },
  {"traAccount" : {
    "accId": 1
  },
    "traDestinationAccount":  {"accId": 2},
    "traAmount": 6600,
    "traDescription": "A"
  },
  {"traAccount" : {
    "accId": 2
  },
    "traDestinationAccount":  {"accId": 1},
    "traAmount": 9000,
    "traDescription": "A"
  },
  {"traAccount" : {
    "accId": 1
  },
    "traDestinationAccount":  {"accId": 2},
    "traAmount": 12900,
    "traDescription": "A"
  },
  {"traAccount" : {
    "accId": 1
  },
    "traDestinationAccount":  {"accId": 2},
    "traAmount": 11200,
    "traDescription": "A"
  },{"traAccount" : {
  "accId": 2
},
  "traDestinationAccount":  {"accId": 1},
  "traAmount": 100120,
  "traDescription": "A"
}

]